{"stats":{"minecraft:custom":{"minecraft:mob_kills":11,"minecraft:inspect_hopper":1,"minecraft:interact_with_crafting_table":29,"minecraft:leave_game":6,"minecraft:time_since_death":418325,"minecraft:sprint_one_cm":601401,"minecraft:walk_one_cm":3694605,"minecraft:drop":18,"minecraft:talked_to_villager":3,"minecraft:deaths":4,"minecraft:sneak_time":2085,"minecraft:walk_under_water_one_cm":31192,"minecraft:jump":3927,"minecraft:walk_on_water_one_cm":91296,"minecraft:interact_with_furnace":196,"minecraft:play_one_minute":838480,"minecraft:sleep_in_bed":1,"minecraft:time_since_rest":418485,"minecraft:waystone_activated":2,"minecraft:damage_taken":4826,"minecraft:damage_dealt":2749,"minecraft:fly_one_cm":378494,"minecraft:open_chest":403,"minecraft:crouch_one_cm":2525,"minecraft:fall_one_cm":76741},"minecraft:picked_up":{"minecraft:charcoal":168,"minecraft:crafting_table":1,"tconstruct:crafting_station":2,"minecraft:azure_bluet":8,"minecraft:chicken":2,"minecraft:clay_ball":488,"exnihilosequentia:mesh_flint":9,"minecraft:lead":1,"exnihilosequentia:piece_nickel":245,"tconstruct:sword":1,"minecraft:oak_stairs":5,"exnihilosequentia:piece_silver":256,"minecraft:gold_block":1,"minecraft:string":556,"integrateddynamics:menril_log":518,"exnihilosequentia:crushed_andesite":42,"exnihilosequentia:dust":801,"minecraft:red_sand":1,"integrateddynamics:menril_berries":426,"minecraft:bucket":1,"integrateddynamics:menril_sapling":82,"minecraft:poppy":4,"minecraft:sugar_cane":6,"minecraft:chest":4,"minecraft:birch_sapling":39,"minecraft:egg":3,"exnihilosequentia:piece_lead":251,"exnihilosequentia:hammer_stone":1,"exnihilosequentia:sieve":1,"minecraft:stick":308,"minecraft:oak_door":2,"minecraft:torch":8,"tconstruct:pickaxe":2,"tconstruct:sky_slime_dirt":1,"ironchest:gold_chest":3,"tconstruct:seared_faucet":3,"minecraft:diorite":5,"minecraft:redstone":201,"exnihilosequentia:crucible_fired":1,"exnihilosequentia:piece_copper":275,"minecraft:stone_sword":2,"minecraft:arrow":8,"minecraft:cactus":1,"minecraft:stone_shovel":1,"minecraft:rotten_flesh":9,"tconstruct:grout":624,"excompressum:chicken_stick":1,"minecraft:obsidian":8,"minecraft:blaze_powder":25,"minecraft:white_wool":29,"minecraft:cobblestone":2027,"minecraft:oxeye_daisy":8,"tconstruct:seared_bricks":7,"minecraft:birch_log":22,"minecraft:feather":4,"minecraft:lilac":1,"integrateddynamics:menril_planks":4,"minecraft:andesite":1,"integrateddynamics:on_the_dynamics_of_integration":1,"integrateddynamics:crystalized_menril_chunk":21,"exnihilosequentia:piece_gold":254,"tconstruct:seared_fuel_tank":1,"exnihilosequentia:piece_tin":246,"minecraft:flint":1836,"tconstruct:copper_block":4,"minecraft:oak_log":629,"minecraft:gunpowder":46,"minecraft:cobblestone_stairs":17,"minecraft:lapis_lazuli":161,"minecraft:dirt":1794,"tconstruct:seared_brick":162,"minecraft:glass":58,"minecraft:bone":3,"minecraft:apple":25,"tconstruct:seared_heater":2,"minecraft:wheat_seeds":163,"minecraft:iron_ingot":10,"minecraft:stone_pickaxe":2,"tconstruct:seared_table":1,"minecraft:iron_ore":88,"integrateddynamics:menril_door":1,"minecraft:glowstone_dust":30,"tconstruct:copper_ingot":3,"thermal:copper_block":1,"minecraft:oak_planks":265,"minecraft:milk_bucket":1,"tconstruct:copper_ore":7,"minecraft:pumpkin":11,"thermal:copper_ingot":6,"minecraft:dandelion":9,"exnihilosequentia:mesh_iron":1,"minecraft:gravel":3744,"minecraft:lava_bucket":1,"minecraft:sand":719,"integrateddynamics:crystalized_menril_block":6,"minecraft:spruce_sapling":13,"minecraft:white_bed":1,"minecraft:spruce_log":13,"exnihilosequentia:crushed_diorite":88,"minecraft:spider_eye":1,"exnihilosequentia:silkworm":423,"exnihilosequentia:cooked_silkworm":31,"minecraft:pumpkin_seeds":3,"tconstruct:seared_basin":2,"minecraft:diamond":6,"minecraft:granite":4,"minecraft:bone_meal":90,"tconstruct:seared_melter":2,"minecraft:emerald":13,"tconstruct:pattern":2,"minecraft:oak_sapling":241,"exnihilosequentia:piece_iron":471,"minecraft:coal":521},"minecraft:broken":{"exnihilosequentia:crook_wood":4,"exnihilosequentia:hammer_stone":7,"minecraft:wooden_pickaxe":1,"minecraft:stone_shovel":9,"excompressum:compressed_hammer_stone":1},"minecraft:killed_by":{"minecraft:creeper":1,"minecraft:spider":1,"minecraft:pillager":1,"minecraft:skeleton":1},"minecraft:crafted":{"exnihilosequentia:mesh_iron":9,"minecraft:brick":31,"minecraft:oak_door":3,"tconstruct:pattern":6,"minecraft:oak_planks":1560,"excompressum:compressed_dust":74,"exnihilosequentia:crucible_fired":1,"exnihilosequentia:porcelain_clay":7,"excompressum:compressed_cobblestone":99,"excompressum:oak_crucible":1,"minecraft:furnace":3,"tconstruct:seared_basin":2,"minecraft:bone_meal":9,"integrateddynamics:menril_planks":192,"tconstruct:seared_melter":1,"minecraft:hopper":7,"minecraft:terracotta":49,"minecraft:glass":8,"integrateddynamics:energy_battery":1,"botanypots:botany_pot":4,"tconstruct:seared_table":1,"minecraft:stone_pickaxe":3,"tconstruct:seared_brick":734,"minecraft:chest":40,"tconstruct:seared_fuel_tank":1,"minecraft:redstone_block":1,"exnihilosequentia:hammer_stone":5,"exnihilosequentia:crucible_unfired":1,"minecraft:flower_pot":3,"exnihilosequentia:mesh_flint":1,"exnihilosequentia:sieve":10,"minecraft:oak_slab":6,"excompressum:compressed_hammer_stone":1,"exnihilosequentia:crook_wood":1,"minecraft:crafting_table":3,"minecraft:spruce_planks":8,"exnihilosequentia:chunk_copper":7,"minecraft:wooden_pickaxe":1,"storagedrawers:oak_full_drawers_1":3,"integrateddynamics:menril_door":6,"tconstruct:seared_drain":3,"minecraft:air":0,"cobblefordays:tier_3":1,"exnihilosequentia:chunk_iron":116,"tconstruct:seared_heater":1,"exnihilosequentia:mesh_string":1,"tconstruct:seared_ingot_gauge":1,"botanypots:hopper_botany_pot":4,"exnihilosequentia:cooked_silkworm":40,"minecraft:charcoal":203,"tconstruct:crafting_station":2,"minecraft:stick":120,"minecraft:iron_ingot":123,"minecraft:oak_stairs":12,"minecraft:stone_sword":2,"tconstruct:seared_faucet":4,"exnihilosequentia:mesh_diamond":1,"excompressum:oak_heavy_sieve":1,"minecraft:white_bed":2,"tconstruct:seared_bricks":66,"exnihilosequentia:chunk_gold":61,"minecraft:torch":88,"integrateddynamics:crystalized_menril_chunk":27,"minecraft:clay":12},"minecraft:mined":{"minecraft:white_bed":1,"minecraft:oak_sapling":5,"minecraft:oak_door":2,"minecraft:cobblestone_stairs":1,"tconstruct:seared_bricks":7,"minecraft:granite":5,"minecraft:red_sand":1,"minecraft:grass_block":1336,"minecraft:spruce_leaves":71,"integrateddynamics:menril_log":198,"minecraft:oxeye_daisy":8,"exnihilosequentia:crushed_diorite":1,"tconstruct:seared_table":1,"integrateddynamics:menril_planks":4,"minecraft:iron_ore":24,"minecraft:fire":1,"ironchest:gold_chest":1,"minecraft:andesite":42,"tconstruct:seared_melter":2,"minecraft:pumpkin":11,"tconstruct:seared_fuel_tank":1,"minecraft:azure_bluet":5,"minecraft:oak_stairs":4,"exnihilosequentia:crucible_fired":1,"minecraft:stone":1382,"tconstruct:sky_slime_dirt":1,"tconstruct:copper_ore":7,"integrateddynamics:menril_door":1,"exnihilosequentia:dust":1,"minecraft:dandelion":3,"minecraft:clay":42,"minecraft:crafting_table":1,"minecraft:torch":3,"tconstruct:seared_basin":2,"minecraft:poppy":4,"excompressum:compressed_cobblestone":227,"minecraft:tall_grass":67,"minecraft:cobblestone":13,"minecraft:oak_planks":72,"minecraft:sugar_cane":4,"minecraft:diorite":81,"minecraft:wall_torch":2,"minecraft:seagrass":1,"minecraft:cactus":1,"tconstruct:seared_faucet":3,"minecraft:birch_log":22,"minecraft:lilac":1,"minecraft:spruce_log":13,"minecraft:birch_leaves":202,"integrateddynamics:menril_log_filled":14,"minecraft:grass":1023,"minecraft:oak_log":402,"minecraft:coal_ore":91,"minecraft:gravel":1589,"minecraft:dirt":381,"minecraft:sand":1173,"tconstruct:crafting_station":2,"tconstruct:seared_heater":2,"integrateddynamics:menril_leaves":525,"minecraft:oak_leaves":2700,"exnihilosequentia:infested_leaves":469},"minecraft:killed":{"minecraft:spider":3,"minecraft:skeleton":3,"minecraft:chicken":1,"excompressum:angry_chicken":1,"minecraft:zombie_villager":1},"minecraft:used":{"storagedrawers:oak_full_drawers_1":5,"exnihilosequentia:hammer_stone":2260,"minecraft:stone_sword":60,"minecraft:red_sand":1,"minecraft:stone_shovel":1357,"minecraft:chest":21,"excompressum:oak_crucible":1,"excompressum:oak_heavy_sieve":1,"excompressum:compressed_hammer_stone":227,"tconstruct:pickaxe":1,"minecraft:oak_door":2,"tconstruct:seared_fuel_tank":2,"minecraft:torch":75,"tconstruct:seared_drain":3,"integrateddynamics:menril_planks_stairs":16,"minecraft:dirt":364,"minecraft:hopper":3,"tconstruct:lavawood":1,"exnihilosequentia:cooked_silkworm":9,"tconstruct:seared_bricks":205,"minecraft:granite":2,"minecraft:milk_bucket":1,"tconstruct:seared_heater":2,"exnihilosequentia:crushed_diorite":1,"minecraft:lava_bucket":3,"excompressum:compressed_cobblestone":227,"integrateddynamics:menril_sapling":11,"minecraft:oak_stairs":48,"tconstruct:seared_faucet":6,"exnihilosequentia:crook_wood":512,"minecraft:oak_sapling":142,"minecraft:furnace":11,"ironchest:gold_chest":2,"tconstruct:smeltery_controller":1,"minecraft:egg":2,"minecraft:water_bucket":18,"minecraft:diorite":1,"minecraft:cobblestone_stairs":45,"minecraft:stone_pickaxe":188,"minecraft:oak_planks":1415,"minecraft:cactus":1,"minecraft:clay":15,"minecraft:wooden_pickaxe":62,"integrateddynamics:menril_log":7,"integrateddynamics:menril_door":7,"minecraft:crafting_table":2,"excompressum:chicken_stick":86,"botanypots:hopper_botany_pot":8,"minecraft:white_bed":4,"tconstruct:seared_basin":4,"integrateddynamics:menril_berries":187,"tconstruct:sky_slime_dirt":1,"cobblefordays:tier_3":1,"minecraft:apple":9,"tconstruct:seared_table":2,"exnihilosequentia:crucible_fired":2,"minecraft:lilac":1,"minecraft:gravel":4,"exnihilosequentia:dust":1,"exnihilosequentia:sieve":10,"tconstruct:seared_melter":2,"minecraft:cobblestone":405,"tconstruct:crafting_station":4,"minecraft:bucket":101,"integrateddynamics:menril_planks":86,"exnihilosequentia:silkworm":6},"minecraft:dropped":{"integrateddynamics:menril_berries":6,"minecraft:lead":1,"tconstruct:slimesteel_block":4,"minecraft:milk_bucket":1,"tconstruct:materials_and_you":1,"theoneprobe:probenote":1,"minecraft:string":1,"minecraft:stone_shovel":1,"integrateddynamics:on_the_dynamics_of_integration":1,"minecraft:wooden_pickaxe":1}},"DataVersion":2586}